LICENSE
logiskip/__init__.py
logiskip/cli.py
logiskip/load.py
logiskip/loads/roundcube/__init__.py
logiskip/util.py
logiskip-0.1.0.post1.dist-info/entry_points.txt
logiskip-0.1.0.post1.dist-info/LICENSE
logiskip-0.1.0.post1.dist-info/WHEEL
logiskip-0.1.0.post1.dist-info/METADATA
logiskip-0.1.0.post1.dist-info/RECORD
