Metadata-Version: 2.1
Name: logiskip
Version: 0.1.0.post1
Summary: Logical database migration between RDBMSs
Home-page: https://github.com/credativ/logiskip
License: Apache-2.0
Keywords: sql,database,migration
Author: Dominik George
Author-email: dominik.george@credativ.de
Requires-Python: >=3.6,<4.0
Classifier: Development Status :: 4 - Beta
Classifier: Environment :: Console
Classifier: Intended Audience :: System Administrators
Classifier: License :: OSI Approved :: Apache Software License
Classifier: Programming Language :: Python :: 3
Classifier: Programming Language :: Python :: 3.6
Classifier: Programming Language :: Python :: 3.7
Classifier: Programming Language :: Python :: 3.8
Classifier: Programming Language :: Python :: 3.9
Classifier: Topic :: Database
Classifier: Topic :: Utilities
Provides-Extra: mysql
Provides-Extra: postgres
Requires-Dist: PyMySQL (>=1.0.2,<2.0.0); extra == "mysql"
Requires-Dist: SQLAlchemy (>=1.4.5,<2.0.0)
Requires-Dist: click (>=7.1.2,<8.0.0)
Requires-Dist: click-logging (>=1.0.1,<2.0.0)
Requires-Dist: pg8000 (>=1.19.1,<2.0.0); extra == "postgres"
Requires-Dist: semantic-version (>=2.8.5,<3.0.0)
Project-URL: Repository, https://github.com/credativ/logiskip
